montag_cleaner/__init__.py
montag_cleaner/montag.py
montag_cleaner/swears.txt
montag_cleaner-1.0.4.dist-info/LICENSE
montag_cleaner-1.0.4.dist-info/METADATA
montag_cleaner-1.0.4.dist-info/WHEEL
montag_cleaner-1.0.4.dist-info/entry_points.txt
montag_cleaner-1.0.4.dist-info/top_level.txt
montag_cleaner-1.0.4.dist-info/RECORD
