Metadata-Version: 2.1
Name: montag-cleaner
Version: 1.0.4
Summary: Montag is a utility which reads e-book files and scrubs them of profanity.
Home-page: https://github.com/mmguero/montag
Author: Seth Grover
Author-email: mero.mero.guero@gmail.com
Project-URL: Bug Tracker, https://github.com/mmguero/montag/issues
Classifier: License :: OSI Approved :: BSD License
Classifier: Programming Language :: Python :: 3
Classifier: Topic :: Text Processing
Requires-Python: >=3.6
License-File: LICENSE
Requires-Dist: python-magic
Requires-Dist: ebooklib
